pyseq/__init__.py
pyseq/args.py
pyseq/check_system.py
pyseq/dcam.py
pyseq/focus.py
pyseq/fpga.py
pyseq/hiseq2500.py
pyseq/image_analysis.py
pyseq/laser.py
pyseq/main.py
pyseq/methods.py
pyseq/objstage.py
pyseq/optics.py
pyseq/pump.py
pyseq/temperature.py
pyseq/valve.py
pyseq/virtualHiSeq.py
pyseq/xstage.py
pyseq/ystage.py
pyseq/zstage.py
pyseq/focus_data/Objective Stack.attrs
pyseq/focus_data/obj_stack_data.txt
pyseq/focus_data/full/c558_RoughScan_x40377_o42248.tiff
pyseq/focus_data/full/c558_RoughScan_x40692_o42248.tiff
pyseq/focus_data/full/c558_RoughScan_x41007_o42248.tiff
pyseq/focus_data/full/c610_RoughScan_x40377_o42248.tiff
pyseq/focus_data/full/c610_RoughScan_x40692_o42248.tiff
pyseq/focus_data/full/c610_RoughScan_x41007_o42248.tiff
pyseq/focus_data/full/c687_RoughScan_x40377_o42248.tiff
pyseq/focus_data/full/c687_RoughScan_x40692_o42248.tiff
pyseq/focus_data/full/c687_RoughScan_x41007_o42248.tiff
pyseq/focus_data/full/c740_RoughScan_x40377_o42248.tiff
pyseq/focus_data/full/c740_RoughScan_x40692_o42248.tiff
pyseq/focus_data/full/c740_RoughScan_x41007_o42248.tiff
pyseq/focus_data/full/machine_name.txt
pyseq/focus_data/full/meta_RoughScan3_x40377_o42248.txt
pyseq/focus_data/full/meta_RoughScan3_x40692_o42248.txt
pyseq/focus_data/full/meta_RoughScan3_x41007_o42248.txt
pyseq/focus_data/partial/c558_RoughScan_x40377_o42248.tiff
pyseq/focus_data/partial/c610_RoughScan_x40377_o42248.tiff
pyseq/focus_data/partial/c687_RoughScan_x40377_o42248.tiff
pyseq/focus_data/partial/c740_RoughScan_x40377_o42248.tiff
pyseq/focus_data/partial/machine_name.txt
pyseq/focus_data/partial/meta_RoughScan3_x40692_o42248.txt
pyseq/recipes/4i.cfg
pyseq/recipes/4i_recipe.txt
pyseq/recipes/__init__.py
pyseq/recipes/background.cfg
pyseq/recipes/com_ports.cfg
pyseq/recipes/dry_image_test.cfg
pyseq/recipes/dry_image_test_recipe.txt
pyseq/recipes/dry_test.cfg
pyseq/recipes/dry_test_recipe.txt
pyseq/recipes/image.cfg
pyseq/recipes/image_recipe.txt
pyseq/recipes/maintenance_wash.cfg
pyseq2500-0.64.dist-info/LICENSE.txt
pyseq2500-0.64.dist-info/METADATA
pyseq2500-0.64.dist-info/WHEEL
pyseq2500-0.64.dist-info/entry_points.txt
pyseq2500-0.64.dist-info/top_level.txt
pyseq2500-0.64.dist-info/RECORD
