Metadata-Version: 2.1
Name: pyseq2500
Version: 0.64
Summary: Control an Illumina HiSeq 2500 System
Home-page: https://github.com/nygctech/PySeq2500
Author: Kunal Pandit
Author-email: kpandit@nygenome.org
License: MIT
Project-URL: Bug Reports, https://github.com/nygctech/PySeq2500/issues
Project-URL: Support, https://www.hackteria.org/wiki/HiSeq2000_-_Next_Level_Hacking#Control_Software
Project-URL: Source, https://github.com/nygctech/PySeq2500
Keywords: sequencing,HiSeq,automation,biology
Platform: UNKNOWN
Classifier: Development Status :: 3 - Alpha
Classifier: License :: OSI Approved :: MIT License
Classifier: Programming Language :: Python :: 3
Classifier: Operating System :: Microsoft :: Windows
Requires-Python: ==3.7*
License-File: LICENSE.txt
Requires-Dist: pyserial (>=3)
Requires-Dist: numpy
Requires-Dist: scipy
Requires-Dist: imageio
Requires-Dist: tabulate
Requires-Dist: dask
Requires-Dist: xarray
Requires-Dist: zarr
Requires-Dist: qtpy
Requires-Dist: napari
Requires-Dist: scikit-image (>=0.17)
Requires-Dist: wmi
Requires-Dist: qtpy (==1.11.2)
Requires-Dist: pyqt5 (==5.15.4)
